dpyrandmeme/__init__.py
dpyrandmeme-1.0.1rc32.post1.dist-info/LICENSE
dpyrandmeme-1.0.1rc32.post1.dist-info/WHEEL
dpyrandmeme-1.0.1rc32.post1.dist-info/METADATA
dpyrandmeme-1.0.1rc32.post1.dist-info/RECORD
